worker_object_server/__init__.py
worker_object_server/object_server.py
worker_object_server/update.py
worker_object_server/update_server.py
worker_object_server-0.1.0.dist-info/LICENSE
worker_object_server-0.1.0.dist-info/METADATA
worker_object_server-0.1.0.dist-info/WHEEL
worker_object_server-0.1.0.dist-info/top_level.txt
worker_object_server-0.1.0.dist-info/RECORD
