Metadata-Version: 2.1
Name: worker-object-server
Version: 0.1.0
Summary: Provides a class mimicking a python dictionary that sends and recieves updates to its connected clients.
Author-email: Oliver Dantzer <oliverdantzer@gmail.com>
Project-URL: Homepage, https://github.com/oliverdantzer/worker-object-server
Project-URL: Issues, https://github.com/oliverdantzer/worker-object-server/issues
Classifier: Programming Language :: Python :: 3
Classifier: Operating System :: OS Independent
Requires-Python: >=3.8
License-File: LICENSE
Requires-Dist: websockets
Requires-Dist: pydantic
Requires-Dist: python-dateutil
